pyfp.cpython-37m-darwin.so
rerf/RerF.py
rerf/__init__.py
rerf/rerfClassifier.py
rerf/urerf.py
rerf-2.0.5.dist-info/METADATA
rerf-2.0.5.dist-info/WHEEL
rerf-2.0.5.dist-info/top_level.txt
rerf-2.0.5.dist-info/RECORD
