Metadata-Version: 2.1
Name: rerf
Version: 2.0.5
Summary: Randomer Forest (RerF) Python Package
Home-page: https://github.com/neurodata/RerF
Author: NeuroData
Author-email: software@neurodata.io
License: Apache License 2.0
Platform: UNKNOWN
Requires-Dist: pybind11 (>=2.2.4)
Requires-Dist: numpy (>=1.16.3)
Requires-Dist: scikit-learn (>=0.21.0)
Requires-Dist: requests (>=2.22.0)
